{
	"info": {
		"_postman_id": "e6229da1-b433-43c5-ba84-125a378f5670",
		"name": "Pruebas_Mongo",
		"schema": "https://schema.getpostman.com/json/collection/v2.1.0/collection.json"
	},
	"item": [
		{
			"name": "Crear un mensaje",
			"request": {
				"method": "POST",
				"header": [],
				"body": {
					"mode": "raw",
					"raw": "{\r\n    \"message\" : \"Test test 1\",\r\n    \"author\" : \"Daniel del Castillo\"\r\n}",
					"options": {
						"raw": {
							"language": "json"
						}
					}
				},
				"url": {
					"raw": "http://localhost:3000/chat/api/messages",
					"protocol": "http",
					"host": [
						"localhost"
					],
					"port": "3000",
					"path": [
						"chat",
						"api",
						"messages"
					]
				}
			},
			"response": []
		},
		{
			"name": "Recibir todos los mensajes",
			"request": {
				"method": "GET",
				"header": [],
				"url": {
					"raw": "http://localhost:3000/chat/api/messages",
					"protocol": "http",
					"host": [
						"localhost"
					],
					"port": "3000",
					"path": [
						"chat",
						"api",
						"messages"
					]
				}
			},
			"response": []
		},
		{
			"name": "Modificar mensaje",
			"request": {
				"method": "PUT",
				"header": [],
				"body": {
					"mode": "raw",
					"raw": "{\r\n    \"message\" : \"Modificado ahora\",\r\n    \"author\" : \"Daniel del Castillo\"\r\n}",
					"options": {
						"raw": {
							"language": "json"
						}
					}
				},
				"url": {
					"raw": "http://localhost:3000/chat/api/messages/1601612359481",
					"protocol": "http",
					"host": [
						"localhost"
					],
					"port": "3000",
					"path": [
						"chat",
						"api",
						"messages",
						"1601612359481"
					]
				}
			},
			"response": []
		},
		{
			"name": "Recibir último mensaje",
			"request": {
				"method": "GET",
				"header": [],
				"url": {
					"raw": "http://localhost:3000/chat/api/messages/1601612359481",
					"protocol": "http",
					"host": [
						"localhost"
					],
					"port": "3000",
					"path": [
						"chat",
						"api",
						"messages",
						"1601612359481"
					]
				}
			},
			"response": []
		},
		{
			"name": "Eliminar último mensaje",
			"request": {
				"method": "DELETE",
				"header": [],
				"url": {
					"raw": "http://localhost:3000/chat/api/messages/1601612359481",
					"protocol": "http",
					"host": [
						"localhost"
					],
					"port": "3000",
					"path": [
						"chat",
						"api",
						"messages",
						"1601612359481"
					]
				}
			},
			"response": []
		}
	],
	"protocolProfileBehavior": {}
}